openhands_resolver/__init__.py
openhands_resolver/github_issue.py
openhands_resolver/io_utils.py
openhands_resolver/issue_definitions.py
openhands_resolver/patching/README.md
openhands_resolver/patching/__init__.py
openhands_resolver/patching/apply.py
openhands_resolver/patching/exceptions.py
openhands_resolver/patching/patch.py
openhands_resolver/patching/snippets.py
openhands_resolver/prompts/guess_success/issue-success-check.jinja
openhands_resolver/prompts/guess_success/pr-feedback-check.jinja
openhands_resolver/prompts/guess_success/pr-review-check.jinja
openhands_resolver/prompts/guess_success/pr-thread-check.jinja
openhands_resolver/prompts/repo_instructions/all-hands-ai___openhands-resolver.txt
openhands_resolver/prompts/repo_instructions/all-hands-ai___openhands.txt
openhands_resolver/prompts/repo_instructions/rbren___rss-parser.txt
openhands_resolver/prompts/resolve/basic-followup.jinja
openhands_resolver/prompts/resolve/basic-with-tests.jinja
openhands_resolver/prompts/resolve/basic.jinja
openhands_resolver/prompts/resolve/pr-changes-summary.jinja
openhands_resolver/resolve_all_issues.py
openhands_resolver/resolve_issue.py
openhands_resolver/resolver_output.py
openhands_resolver/send_pull_request.py
openhands_resolver/utils.py
openhands_resolver/visualize_resolver_output.py
poetry.lock
openhands_resolver-0.3.1.dist-info/LICENSE
openhands_resolver-0.3.1.dist-info/METADATA
openhands_resolver-0.3.1.dist-info/WHEEL
openhands_resolver-0.3.1.dist-info/RECORD
