Metadata-Version: 2.1
Name: openhands-resolver
Version: 0.3.1
Summary: OpenHands Issue Resolver
Home-page: https://github.com/All-Hands-AI/openhands-resolver
License: MIT
Author: All Hands AI
Requires-Python: >=3.12,<4.0
Classifier: License :: OSI Approved :: MIT License
Classifier: Programming Language :: Python :: 3
Classifier: Programming Language :: Python :: 3.12
Requires-Dist: openhands-ai (>=0.13.1,<0.14.0)
Requires-Dist: pandas (>=2.2.3,<3.0.0)
Project-URL: Repository, https://github.com/All-Hands-AI/openhands-resolver
